graphem/__init__.py
graphem/benchmark.py
graphem/datasets.py
graphem/embedder.py
graphem/generators.py
graphem/index.py
graphem/influence.py
graphem/visualization.py
graphem_jax-0.1.0.dist-info/licenses/LICENSE
graphem_jax-0.1.0.dist-info/METADATA
graphem_jax-0.1.0.dist-info/WHEEL
graphem_jax-0.1.0.dist-info/top_level.txt
graphem_jax-0.1.0.dist-info/RECORD
